{
  "Id": "be712461-7fbe-49eb-a2ec-ca6b8dda1ca4",
  "Name": "Schedule",
  "OriginalName": "Schedule",
  "NamePlural": "Schedules",
  "DatabaseTableName": "Schedules",
  "Namespace": "Schedules",
  "BaseClass": "FullAuditedAggregateRoot",
  "MenuIcon": "calendar-alt",
  "PrimaryKeyType": "Guid",
  "PreserveCustomCode": true,
  "IsMultiTenant": false,
  "CheckConcurrency": true,
  "ShouldCreateUserInterface": true,
  "ShouldCreateBackend": true,
  "ShouldExportExcel": true,
  "ShouldAddMigration": true,
  "ShouldUpdateDatabase": true,
  "CreateTests": false,
  "Properties": [
    {
      "Id": "6682f865-fef7-46bc-b3a6-f96c3be3c637",
      "Name": "Code",
      "Type": "string",
      "EnumType": "",
      "EnumNamespace": "",
      "EnumAngularImport": "shared/enums",
      "EnumFilePath": null,
      "DefaultValue": null,
      "IsNullable": false,
      "IsRequired": false,
      "AllowEmptyStrings": false,
      "IsTextArea": false,
      "MinLength": null,
      "MaxLength": null,
      "SortOrder": 0,
      "SortType": 0,
      "Regex": "",
      "EmailValidation": false,
      "ShowOnList": true,
      "ShowOnCreateModal": true,
      "ShowOnEditModal": true,
      "ReadonlyOnEditModal": false,
      "EnumValues": null,
      "IsSelected": true,
      "OrdinalIndex": 0
    },
    {
      "Id": "b55fe500-1116-41f6-b555-810056dbdc9b",
      "Name": "Name",
      "Type": "string",
      "EnumType": "",
      "EnumNamespace": "",
      "EnumAngularImport": "shared/enums",
      "EnumFilePath": null,
      "DefaultValue": null,
      "IsNullable": false,
      "IsRequired": false,
      "AllowEmptyStrings": false,
      "IsTextArea": false,
      "MinLength": null,
      "MaxLength": null,
      "SortOrder": 0,
      "SortType": 0,
      "Regex": "",
      "EmailValidation": false,
      "ShowOnList": true,
      "ShowOnCreateModal": true,
      "ShowOnEditModal": true,
      "ReadonlyOnEditModal": false,
      "EnumValues": null,
      "IsSelected": true,
      "OrdinalIndex": 0
    },
    {
      "Id": "851c21f2-efd7-4c61-ac9d-6ca50254dae5",
      "Name": "DateFrom",
      "Type": "DateTime",
      "EnumType": "",
      "EnumNamespace": "",
      "EnumAngularImport": "shared/enums",
      "EnumFilePath": null,
      "DefaultValue": null,
      "IsNullable": false,
      "IsRequired": false,
      "AllowEmptyStrings": false,
      "IsTextArea": false,
      "MinLength": null,
      "MaxLength": null,
      "SortOrder": 0,
      "SortType": 0,
      "Regex": "",
      "EmailValidation": false,
      "ShowOnList": true,
      "ShowOnCreateModal": true,
      "ShowOnEditModal": true,
      "ReadonlyOnEditModal": false,
      "EnumValues": null,
      "IsSelected": true,
      "OrdinalIndex": 0
    },
    {
      "Id": "707ab962-abeb-4390-aaa1-2fc9b1467e2b",
      "Name": "DateTo",
      "Type": "DateTime",
      "EnumType": "",
      "EnumNamespace": "",
      "EnumAngularImport": "shared/enums",
      "EnumFilePath": null,
      "DefaultValue": null,
      "IsNullable": false,
      "IsRequired": false,
      "AllowEmptyStrings": false,
      "IsTextArea": false,
      "MinLength": null,
      "MaxLength": null,
      "SortOrder": 0,
      "SortType": 0,
      "Regex": "",
      "EmailValidation": false,
      "ShowOnList": true,
      "ShowOnCreateModal": true,
      "ShowOnEditModal": true,
      "ReadonlyOnEditModal": false,
      "EnumValues": null,
      "IsSelected": true,
      "OrdinalIndex": 0
    },
    {
      "Id": "7ffb599d-1114-4a9c-a899-d46ad5213f17",
      "Name": "Note",
      "Type": "string",
      "EnumType": "",
      "EnumNamespace": "",
      "EnumAngularImport": "shared/enums",
      "EnumFilePath": null,
      "DefaultValue": null,
      "IsNullable": false,
      "IsRequired": false,
      "AllowEmptyStrings": false,
      "IsTextArea": true,
      "MinLength": null,
      "MaxLength": null,
      "SortOrder": 0,
      "SortType": 0,
      "Regex": "",
      "EmailValidation": false,
      "ShowOnList": true,
      "ShowOnCreateModal": true,
      "ShowOnEditModal": true,
      "ReadonlyOnEditModal": false,
      "EnumValues": null,
      "IsSelected": true,
      "OrdinalIndex": 0
    }
  ],
  "NavigationProperties": [
    {
      "EntityNameWithDuplicationNumber": "Staff",
      "EntitySetNameWithDuplicationNumber": "Staffs",
      "ReferencePropertyName": "Staff",
      "UiPickType": "Dropdown",
      "IsRequired": true,
      "Name": "StaffId",
      "DisplayProperty": "Code",
      "Namespace": "FaceAPI.Staffs",
      "EntityName": "Staff",
      "EntitySetName": "Staffs",
      "DtoNamespace": "FaceAPI.Staffs",
      "DtoEntityName": "StaffDto",
      "Type": "Guid"
    }
  ],
  "NavigationConnections": [
    {
      "Name": "ScheduleDetails",
      "DisplayProperty": "Name",
      "Namespace": "FaceAPI.ScheduleDetails",
      "EntityName": "ScheduleDetail",
      "EntitySetName": "ScheduleDetails",
      "DtoNamespace": "FaceAPI.ScheduleDetails",
      "DtoEntityName": "ScheduleDetailDto",
      "Type": "Guid"
    }
  ],
  "PhysicalFileName": "Schedule.json"
}